{
  "openapi": "3.0.1",
  "info": {
    "title": "Final-year-Project",
    "version": "1.0"
  },
  "paths": {
    "/api/Camera": {
      "get": {
        "tags": [
          "Camera"
        ],
        "responses": {
          "200": {
            "description": "OK",
            "content": {
              "text/plain": {
                "schema": {
                  "type": "array",
                  "items": {
                    "$ref": "#/components/schemas/CameraDto"
                  }
                }
              },
              "application/json": {
                "schema": {
                  "type": "array",
                  "items": {
                    "$ref": "#/components/schemas/CameraDto"
                  }
                }
              },
              "text/json": {
                "schema": {
                  "type": "array",
                  "items": {
                    "$ref": "#/components/schemas/CameraDto"
                  }
                }
              }
            }
          }
        }
      },
      "post": {
        "tags": [
          "Camera"
        ],
        "requestBody": {
          "content": {
            "application/json": {
              "schema": {
                "$ref": "#/components/schemas/CreateCameraDto"
              }
            },
            "text/json": {
              "schema": {
                "$ref": "#/components/schemas/CreateCameraDto"
              }
            },
            "application/*+json": {
              "schema": {
                "$ref": "#/components/schemas/CreateCameraDto"
              }
            }
          }
        },
        "responses": {
          "200": {
            "description": "OK",
            "content": {
              "text/plain": {
                "schema": {
                  "$ref": "#/components/schemas/CameraDto"
                }
              },
              "application/json": {
                "schema": {
                  "$ref": "#/components/schemas/CameraDto"
                }
              },
              "text/json": {
                "schema": {
                  "$ref": "#/components/schemas/CameraDto"
                }
              }
            }
          }
        }
      }
    },
    "/api/Camera/{id}": {
      "get": {
        "tags": [
          "Camera"
        ],
        "parameters": [
          {
            "name": "id",
            "in": "path",
            "required": true,
            "schema": {
              "type": "integer",
              "format": "int32"
            }
          }
        ],
        "responses": {
          "200": {
            "description": "OK",
            "content": {
              "text/plain": {
                "schema": {
                  "$ref": "#/components/schemas/CameraDto"
                }
              },
              "application/json": {
                "schema": {
                  "$ref": "#/components/schemas/CameraDto"
                }
              },
              "text/json": {
                "schema": {
                  "$ref": "#/components/schemas/CameraDto"
                }
              }
            }
          }
        }
      },
      "put": {
        "tags": [
          "Camera"
        ],
        "parameters": [
          {
            "name": "id",
            "in": "path",
            "required": true,
            "schema": {
              "type": "integer",
              "format": "int32"
            }
          }
        ],
        "requestBody": {
          "content": {
            "application/json": {
              "schema": {
                "$ref": "#/components/schemas/UpdateCameraDto"
              }
            },
            "text/json": {
              "schema": {
                "$ref": "#/components/schemas/UpdateCameraDto"
              }
            },
            "application/*+json": {
              "schema": {
                "$ref": "#/components/schemas/UpdateCameraDto"
              }
            }
          }
        },
        "responses": {
          "200": {
            "description": "OK",
            "content": {
              "text/plain": {
                "schema": {
                  "$ref": "#/components/schemas/CameraDto"
                }
              },
              "application/json": {
                "schema": {
                  "$ref": "#/components/schemas/CameraDto"
                }
              },
              "text/json": {
                "schema": {
                  "$ref": "#/components/schemas/CameraDto"
                }
              }
            }
          }
        }
      },
      "delete": {
        "tags": [
          "Camera"
        ],
        "parameters": [
          {
            "name": "id",
            "in": "path",
            "required": true,
            "schema": {
              "type": "integer",
              "format": "int32"
            }
          }
        ],
        "responses": {
          "200": {
            "description": "OK"
          }
        }
      }
    },
    "/api/Computer": {
      "get": {
        "tags": [
          "Computer"
        ],
        "responses": {
          "200": {
            "description": "OK",
            "content": {
              "text/plain": {
                "schema": {
                  "type": "array",
                  "items": {
                    "$ref": "#/components/schemas/ComputerDto"
                  }
                }
              },
              "application/json": {
                "schema": {
                  "type": "array",
                  "items": {
                    "$ref": "#/components/schemas/ComputerDto"
                  }
                }
              },
              "text/json": {
                "schema": {
                  "type": "array",
                  "items": {
                    "$ref": "#/components/schemas/ComputerDto"
                  }
                }
              }
            }
          }
        }
      },
      "post": {
        "tags": [
          "Computer"
        ],
        "requestBody": {
          "content": {
            "application/json": {
              "schema": {
                "$ref": "#/components/schemas/CreateComputerDto"
              }
            },
            "text/json": {
              "schema": {
                "$ref": "#/components/schemas/CreateComputerDto"
              }
            },
            "application/*+json": {
              "schema": {
                "$ref": "#/components/schemas/CreateComputerDto"
              }
            }
          }
        },
        "responses": {
          "200": {
            "description": "OK",
            "content": {
              "text/plain": {
                "schema": {
                  "$ref": "#/components/schemas/ComputerDto"
                }
              },
              "application/json": {
                "schema": {
                  "$ref": "#/components/schemas/ComputerDto"
                }
              },
              "text/json": {
                "schema": {
                  "$ref": "#/components/schemas/ComputerDto"
                }
              }
            }
          }
        }
      }
    },
    "/api/Computer/{id}": {
      "get": {
        "tags": [
          "Computer"
        ],
        "parameters": [
          {
            "name": "id",
            "in": "path",
            "required": true,
            "schema": {
              "type": "integer",
              "format": "int32"
            }
          }
        ],
        "responses": {
          "200": {
            "description": "OK",
            "content": {
              "text/plain": {
                "schema": {
                  "$ref": "#/components/schemas/ComputerDto"
                }
              },
              "application/json": {
                "schema": {
                  "$ref": "#/components/schemas/ComputerDto"
                }
              },
              "text/json": {
                "schema": {
                  "$ref": "#/components/schemas/ComputerDto"
                }
              }
            }
          }
        }
      },
      "put": {
        "tags": [
          "Computer"
        ],
        "parameters": [
          {
            "name": "id",
            "in": "path",
            "required": true,
            "schema": {
              "type": "integer",
              "format": "int32"
            }
          }
        ],
        "requestBody": {
          "content": {
            "application/json": {
              "schema": {
                "$ref": "#/components/schemas/UpdateComputerDto"
              }
            },
            "text/json": {
              "schema": {
                "$ref": "#/components/schemas/UpdateComputerDto"
              }
            },
            "application/*+json": {
              "schema": {
                "$ref": "#/components/schemas/UpdateComputerDto"
              }
            }
          }
        },
        "responses": {
          "200": {
            "description": "OK",
            "content": {
              "text/plain": {
                "schema": {
                  "$ref": "#/components/schemas/ComputerDto"
                }
              },
              "application/json": {
                "schema": {
                  "$ref": "#/components/schemas/ComputerDto"
                }
              },
              "text/json": {
                "schema": {
                  "$ref": "#/components/schemas/ComputerDto"
                }
              }
            }
          }
        }
      },
      "delete": {
        "tags": [
          "Computer"
        ],
        "parameters": [
          {
            "name": "id",
            "in": "path",
            "required": true,
            "schema": {
              "type": "integer",
              "format": "int32"
            }
          }
        ],
        "responses": {
          "200": {
            "description": "OK"
          }
        }
      }
    },
    "/api/ControlUnit": {
      "get": {
        "tags": [
          "ControlUnit"
        ],
        "responses": {
          "200": {
            "description": "OK",
            "content": {
              "text/plain": {
                "schema": {
                  "type": "array",
                  "items": {
                    "$ref": "#/components/schemas/ControlUnitDto"
                  }
                }
              },
              "application/json": {
                "schema": {
                  "type": "array",
                  "items": {
                    "$ref": "#/components/schemas/ControlUnitDto"
                  }
                }
              },
              "text/json": {
                "schema": {
                  "type": "array",
                  "items": {
                    "$ref": "#/components/schemas/ControlUnitDto"
                  }
                }
              }
            }
          }
        }
      },
      "post": {
        "tags": [
          "ControlUnit"
        ],
        "requestBody": {
          "content": {
            "application/json": {
              "schema": {
                "$ref": "#/components/schemas/CreateControlUnitDto"
              }
            },
            "text/json": {
              "schema": {
                "$ref": "#/components/schemas/CreateControlUnitDto"
              }
            },
            "application/*+json": {
              "schema": {
                "$ref": "#/components/schemas/CreateControlUnitDto"
              }
            }
          }
        },
        "responses": {
          "200": {
            "description": "OK",
            "content": {
              "text/plain": {
                "schema": {
                  "$ref": "#/components/schemas/ControlUnitDto"
                }
              },
              "application/json": {
                "schema": {
                  "$ref": "#/components/schemas/ControlUnitDto"
                }
              },
              "text/json": {
                "schema": {
                  "$ref": "#/components/schemas/ControlUnitDto"
                }
              }
            }
          }
        }
      }
    },
    "/api/ControlUnit/{id}": {
      "get": {
        "tags": [
          "ControlUnit"
        ],
        "parameters": [
          {
            "name": "id",
            "in": "path",
            "required": true,
            "schema": {
              "type": "integer",
              "format": "int32"
            }
          }
        ],
        "responses": {
          "200": {
            "description": "OK",
            "content": {
              "text/plain": {
                "schema": {
                  "$ref": "#/components/schemas/ControlUnitDto"
                }
              },
              "application/json": {
                "schema": {
                  "$ref": "#/components/schemas/ControlUnitDto"
                }
              },
              "text/json": {
                "schema": {
                  "$ref": "#/components/schemas/ControlUnitDto"
                }
              }
            }
          }
        }
      },
      "put": {
        "tags": [
          "ControlUnit"
        ],
        "parameters": [
          {
            "name": "id",
            "in": "path",
            "required": true,
            "schema": {
              "type": "integer",
              "format": "int32"
            }
          }
        ],
        "requestBody": {
          "content": {
            "application/json": {
              "schema": {
                "$ref": "#/components/schemas/UpdateControlUnitDto"
              }
            },
            "text/json": {
              "schema": {
                "$ref": "#/components/schemas/UpdateControlUnitDto"
              }
            },
            "application/*+json": {
              "schema": {
                "$ref": "#/components/schemas/UpdateControlUnitDto"
              }
            }
          }
        },
        "responses": {
          "200": {
            "description": "OK",
            "content": {
              "text/plain": {
                "schema": {
                  "$ref": "#/components/schemas/ControlUnitDto"
                }
              },
              "application/json": {
                "schema": {
                  "$ref": "#/components/schemas/ControlUnitDto"
                }
              },
              "text/json": {
                "schema": {
                  "$ref": "#/components/schemas/ControlUnitDto"
                }
              }
            }
          }
        }
      },
      "delete": {
        "tags": [
          "ControlUnit"
        ],
        "parameters": [
          {
            "name": "id",
            "in": "path",
            "required": true,
            "schema": {
              "type": "integer",
              "format": "int32"
            }
          }
        ],
        "responses": {
          "200": {
            "description": "OK"
          }
        }
      }
    },
    "/api/Customer": {
      "get": {
        "tags": [
          "Customer"
        ],
        "responses": {
          "200": {
            "description": "OK",
            "content": {
              "text/plain": {
                "schema": {
                  "type": "array",
                  "items": {
                    "$ref": "#/components/schemas/CustomerDto"
                  }
                }
              },
              "application/json": {
                "schema": {
                  "type": "array",
                  "items": {
                    "$ref": "#/components/schemas/CustomerDto"
                  }
                }
              },
              "text/json": {
                "schema": {
                  "type": "array",
                  "items": {
                    "$ref": "#/components/schemas/CustomerDto"
                  }
                }
              }
            }
          }
        }
      },
      "post": {
        "tags": [
          "Customer"
        ],
        "requestBody": {
          "content": {
            "application/json": {
              "schema": {
                "$ref": "#/components/schemas/CreateCustomerDto"
              }
            },
            "text/json": {
              "schema": {
                "$ref": "#/components/schemas/CreateCustomerDto"
              }
            },
            "application/*+json": {
              "schema": {
                "$ref": "#/components/schemas/CreateCustomerDto"
              }
            }
          }
        },
        "responses": {
          "200": {
            "description": "OK",
            "content": {
              "text/plain": {
                "schema": {
                  "$ref": "#/components/schemas/CustomerDto"
                }
              },
              "application/json": {
                "schema": {
                  "$ref": "#/components/schemas/CustomerDto"
                }
              },
              "text/json": {
                "schema": {
                  "$ref": "#/components/schemas/CustomerDto"
                }
              }
            }
          }
        }
      }
    },
    "/api/Customer/{id}": {
      "get": {
        "tags": [
          "Customer"
        ],
        "parameters": [
          {
            "name": "id",
            "in": "path",
            "required": true,
            "schema": {
              "type": "integer",
              "format": "int32"
            }
          }
        ],
        "responses": {
          "200": {
            "description": "OK",
            "content": {
              "text/plain": {
                "schema": {
                  "$ref": "#/components/schemas/CustomerDto"
                }
              },
              "application/json": {
                "schema": {
                  "$ref": "#/components/schemas/CustomerDto"
                }
              },
              "text/json": {
                "schema": {
                  "$ref": "#/components/schemas/CustomerDto"
                }
              }
            }
          }
        }
      },
      "put": {
        "tags": [
          "Customer"
        ],
        "parameters": [
          {
            "name": "id",
            "in": "path",
            "required": true,
            "schema": {
              "type": "integer",
              "format": "int32"
            }
          }
        ],
        "requestBody": {
          "content": {
            "application/json": {
              "schema": {
                "$ref": "#/components/schemas/UpdateCustomerDto"
              }
            },
            "text/json": {
              "schema": {
                "$ref": "#/components/schemas/UpdateCustomerDto"
              }
            },
            "application/*+json": {
              "schema": {
                "$ref": "#/components/schemas/UpdateCustomerDto"
              }
            }
          }
        },
        "responses": {
          "200": {
            "description": "OK",
            "content": {
              "text/plain": {
                "schema": {
                  "$ref": "#/components/schemas/CustomerDto"
                }
              },
              "application/json": {
                "schema": {
                  "$ref": "#/components/schemas/CustomerDto"
                }
              },
              "text/json": {
                "schema": {
                  "$ref": "#/components/schemas/CustomerDto"
                }
              }
            }
          }
        }
      },
      "delete": {
        "tags": [
          "Customer"
        ],
        "parameters": [
          {
            "name": "id",
            "in": "path",
            "required": true,
            "schema": {
              "type": "integer",
              "format": "int32"
            }
          }
        ],
        "responses": {
          "200": {
            "description": "OK"
          }
        }
      }
    },
    "/api/CustomerGroup": {
      "get": {
        "tags": [
          "CustomerGroup"
        ],
        "responses": {
          "200": {
            "description": "OK",
            "content": {
              "text/plain": {
                "schema": {
                  "type": "array",
                  "items": {
                    "$ref": "#/components/schemas/CustomerGroupDto"
                  }
                }
              },
              "application/json": {
                "schema": {
                  "type": "array",
                  "items": {
                    "$ref": "#/components/schemas/CustomerGroupDto"
                  }
                }
              },
              "text/json": {
                "schema": {
                  "type": "array",
                  "items": {
                    "$ref": "#/components/schemas/CustomerGroupDto"
                  }
                }
              }
            }
          }
        }
      },
      "post": {
        "tags": [
          "CustomerGroup"
        ],
        "requestBody": {
          "content": {
            "application/json": {
              "schema": {
                "$ref": "#/components/schemas/CreateCustomerGroupDto"
              }
            },
            "text/json": {
              "schema": {
                "$ref": "#/components/schemas/CreateCustomerGroupDto"
              }
            },
            "application/*+json": {
              "schema": {
                "$ref": "#/components/schemas/CreateCustomerGroupDto"
              }
            }
          }
        },
        "responses": {
          "200": {
            "description": "OK",
            "content": {
              "text/plain": {
                "schema": {
                  "$ref": "#/components/schemas/CustomerGroupDto"
                }
              },
              "application/json": {
                "schema": {
                  "$ref": "#/components/schemas/CustomerGroupDto"
                }
              },
              "text/json": {
                "schema": {
                  "$ref": "#/components/schemas/CustomerGroupDto"
                }
              }
            }
          }
        }
      }
    },
    "/api/CustomerGroup/{id}": {
      "get": {
        "tags": [
          "CustomerGroup"
        ],
        "parameters": [
          {
            "name": "id",
            "in": "path",
            "required": true,
            "schema": {
              "type": "integer",
              "format": "int32"
            }
          }
        ],
        "responses": {
          "200": {
            "description": "OK",
            "content": {
              "text/plain": {
                "schema": {
                  "$ref": "#/components/schemas/CustomerGroupDto"
                }
              },
              "application/json": {
                "schema": {
                  "$ref": "#/components/schemas/CustomerGroupDto"
                }
              },
              "text/json": {
                "schema": {
                  "$ref": "#/components/schemas/CustomerGroupDto"
                }
              }
            }
          }
        }
      },
      "put": {
        "tags": [
          "CustomerGroup"
        ],
        "parameters": [
          {
            "name": "id",
            "in": "path",
            "required": true,
            "schema": {
              "type": "integer",
              "format": "int32"
            }
          }
        ],
        "requestBody": {
          "content": {
            "application/json": {
              "schema": {
                "$ref": "#/components/schemas/UpdateCustomerGroupDto"
              }
            },
            "text/json": {
              "schema": {
                "$ref": "#/components/schemas/UpdateCustomerGroupDto"
              }
            },
            "application/*+json": {
              "schema": {
                "$ref": "#/components/schemas/UpdateCustomerGroupDto"
              }
            }
          }
        },
        "responses": {
          "200": {
            "description": "OK",
            "content": {
              "text/plain": {
                "schema": {
                  "$ref": "#/components/schemas/CustomerGroupDto"
                }
              },
              "application/json": {
                "schema": {
                  "$ref": "#/components/schemas/CustomerGroupDto"
                }
              },
              "text/json": {
                "schema": {
                  "$ref": "#/components/schemas/CustomerGroupDto"
                }
              }
            }
          }
        }
      },
      "delete": {
        "tags": [
          "CustomerGroup"
        ],
        "parameters": [
          {
            "name": "id",
            "in": "path",
            "required": true,
            "schema": {
              "type": "integer",
              "format": "int32"
            }
          }
        ],
        "responses": {
          "200": {
            "description": "OK"
          }
        }
      }
    },
    "/api/Gate": {
      "get": {
        "tags": [
          "Gate"
        ],
        "responses": {
          "200": {
            "description": "OK",
            "content": {
              "text/plain": {
                "schema": {
                  "type": "array",
                  "items": {
                    "$ref": "#/components/schemas/GateDto"
                  }
                }
              },
              "application/json": {
                "schema": {
                  "type": "array",
                  "items": {
                    "$ref": "#/components/schemas/GateDto"
                  }
                }
              },
              "text/json": {
                "schema": {
                  "type": "array",
                  "items": {
                    "$ref": "#/components/schemas/GateDto"
                  }
                }
              }
            }
          }
        }
      },
      "post": {
        "tags": [
          "Gate"
        ],
        "requestBody": {
          "content": {
            "application/json": {
              "schema": {
                "$ref": "#/components/schemas/CreateGateDto"
              }
            },
            "text/json": {
              "schema": {
                "$ref": "#/components/schemas/CreateGateDto"
              }
            },
            "application/*+json": {
              "schema": {
                "$ref": "#/components/schemas/CreateGateDto"
              }
            }
          }
        },
        "responses": {
          "200": {
            "description": "OK",
            "content": {
              "text/plain": {
                "schema": {
                  "$ref": "#/components/schemas/GateDto"
                }
              },
              "application/json": {
                "schema": {
                  "$ref": "#/components/schemas/GateDto"
                }
              },
              "text/json": {
                "schema": {
                  "$ref": "#/components/schemas/GateDto"
                }
              }
            }
          }
        }
      }
    },
    "/api/Gate/{id}": {
      "get": {
        "tags": [
          "Gate"
        ],
        "parameters": [
          {
            "name": "id",
            "in": "path",
            "required": true,
            "schema": {
              "type": "integer",
              "format": "int32"
            }
          }
        ],
        "responses": {
          "200": {
            "description": "OK",
            "content": {
              "text/plain": {
                "schema": {
                  "$ref": "#/components/schemas/GateDto"
                }
              },
              "application/json": {
                "schema": {
                  "$ref": "#/components/schemas/GateDto"
                }
              },
              "text/json": {
                "schema": {
                  "$ref": "#/components/schemas/GateDto"
                }
              }
            }
          }
        }
      },
      "put": {
        "tags": [
          "Gate"
        ],
        "parameters": [
          {
            "name": "id",
            "in": "path",
            "required": true,
            "schema": {
              "type": "integer",
              "format": "int32"
            }
          }
        ],
        "requestBody": {
          "content": {
            "application/json": {
              "schema": {
                "$ref": "#/components/schemas/UpdateGateDto"
              }
            },
            "text/json": {
              "schema": {
                "$ref": "#/components/schemas/UpdateGateDto"
              }
            },
            "application/*+json": {
              "schema": {
                "$ref": "#/components/schemas/UpdateGateDto"
              }
            }
          }
        },
        "responses": {
          "200": {
            "description": "OK",
            "content": {
              "text/plain": {
                "schema": {
                  "$ref": "#/components/schemas/GateDto"
                }
              },
              "application/json": {
                "schema": {
                  "$ref": "#/components/schemas/GateDto"
                }
              },
              "text/json": {
                "schema": {
                  "$ref": "#/components/schemas/GateDto"
                }
              }
            }
          }
        }
      },
      "delete": {
        "tags": [
          "Gate"
        ],
        "parameters": [
          {
            "name": "id",
            "in": "path",
            "required": true,
            "schema": {
              "type": "integer",
              "format": "int32"
            }
          }
        ],
        "responses": {
          "200": {
            "description": "OK"
          }
        }
      }
    },
    "/api/Lane": {
      "get": {
        "tags": [
          "Lane"
        ],
        "responses": {
          "200": {
            "description": "OK",
            "content": {
              "text/plain": {
                "schema": {
                  "type": "array",
                  "items": {
                    "$ref": "#/components/schemas/LaneDto"
                  }
                }
              },
              "application/json": {
                "schema": {
                  "type": "array",
                  "items": {
                    "$ref": "#/components/schemas/LaneDto"
                  }
                }
              },
              "text/json": {
                "schema": {
                  "type": "array",
                  "items": {
                    "$ref": "#/components/schemas/LaneDto"
                  }
                }
              }
            }
          }
        }
      },
      "post": {
        "tags": [
          "Lane"
        ],
        "requestBody": {
          "content": {
            "application/json": {
              "schema": {
                "$ref": "#/components/schemas/CreateLaneDto"
              }
            },
            "text/json": {
              "schema": {
                "$ref": "#/components/schemas/CreateLaneDto"
              }
            },
            "application/*+json": {
              "schema": {
                "$ref": "#/components/schemas/CreateLaneDto"
              }
            }
          }
        },
        "responses": {
          "200": {
            "description": "OK",
            "content": {
              "text/plain": {
                "schema": {
                  "$ref": "#/components/schemas/LaneDto"
                }
              },
              "application/json": {
                "schema": {
                  "$ref": "#/components/schemas/LaneDto"
                }
              },
              "text/json": {
                "schema": {
                  "$ref": "#/components/schemas/LaneDto"
                }
              }
            }
          }
        }
      }
    },
    "/api/Lane/{id}": {
      "get": {
        "tags": [
          "Lane"
        ],
        "parameters": [
          {
            "name": "id",
            "in": "path",
            "required": true,
            "schema": {
              "type": "integer",
              "format": "int32"
            }
          }
        ],
        "responses": {
          "200": {
            "description": "OK",
            "content": {
              "text/plain": {
                "schema": {
                  "$ref": "#/components/schemas/LaneDto"
                }
              },
              "application/json": {
                "schema": {
                  "$ref": "#/components/schemas/LaneDto"
                }
              },
              "text/json": {
                "schema": {
                  "$ref": "#/components/schemas/LaneDto"
                }
              }
            }
          }
        }
      },
      "put": {
        "tags": [
          "Lane"
        ],
        "parameters": [
          {
            "name": "id",
            "in": "path",
            "required": true,
            "schema": {
              "type": "integer",
              "format": "int32"
            }
          }
        ],
        "requestBody": {
          "content": {
            "application/json": {
              "schema": {
                "$ref": "#/components/schemas/UpdateLaneDto"
              }
            },
            "text/json": {
              "schema": {
                "$ref": "#/components/schemas/UpdateLaneDto"
              }
            },
            "application/*+json": {
              "schema": {
                "$ref": "#/components/schemas/UpdateLaneDto"
              }
            }
          }
        },
        "responses": {
          "200": {
            "description": "OK",
            "content": {
              "text/plain": {
                "schema": {
                  "$ref": "#/components/schemas/LaneDto"
                }
              },
              "application/json": {
                "schema": {
                  "$ref": "#/components/schemas/LaneDto"
                }
              },
              "text/json": {
                "schema": {
                  "$ref": "#/components/schemas/LaneDto"
                }
              }
            }
          }
        }
      },
      "delete": {
        "tags": [
          "Lane"
        ],
        "parameters": [
          {
            "name": "id",
            "in": "path",
            "required": true,
            "schema": {
              "type": "integer",
              "format": "int32"
            }
          }
        ],
        "responses": {
          "200": {
            "description": "OK"
          }
        }
      }
    },
    "/api/Led": {
      "get": {
        "tags": [
          "Led"
        ],
        "responses": {
          "200": {
            "description": "OK",
            "content": {
              "text/plain": {
                "schema": {
                  "type": "array",
                  "items": {
                    "$ref": "#/components/schemas/LedDto"
                  }
                }
              },
              "application/json": {
                "schema": {
                  "type": "array",
                  "items": {
                    "$ref": "#/components/schemas/LedDto"
                  }
                }
              },
              "text/json": {
                "schema": {
                  "type": "array",
                  "items": {
                    "$ref": "#/components/schemas/LedDto"
                  }
                }
              }
            }
          }
        }
      },
      "post": {
        "tags": [
          "Led"
        ],
        "requestBody": {
          "content": {
            "application/json": {
              "schema": {
                "$ref": "#/components/schemas/CreateLedDto"
              }
            },
            "text/json": {
              "schema": {
                "$ref": "#/components/schemas/CreateLedDto"
              }
            },
            "application/*+json": {
              "schema": {
                "$ref": "#/components/schemas/CreateLedDto"
              }
            }
          }
        },
        "responses": {
          "200": {
            "description": "OK",
            "content": {
              "text/plain": {
                "schema": {
                  "$ref": "#/components/schemas/LedDto"
                }
              },
              "application/json": {
                "schema": {
                  "$ref": "#/components/schemas/LedDto"
                }
              },
              "text/json": {
                "schema": {
                  "$ref": "#/components/schemas/LedDto"
                }
              }
            }
          }
        }
      }
    },
    "/api/Led/{id}": {
      "get": {
        "tags": [
          "Led"
        ],
        "parameters": [
          {
            "name": "id",
            "in": "path",
            "required": true,
            "schema": {
              "type": "integer",
              "format": "int32"
            }
          }
        ],
        "responses": {
          "200": {
            "description": "OK",
            "content": {
              "text/plain": {
                "schema": {
                  "$ref": "#/components/schemas/LedDto"
                }
              },
              "application/json": {
                "schema": {
                  "$ref": "#/components/schemas/LedDto"
                }
              },
              "text/json": {
                "schema": {
                  "$ref": "#/components/schemas/LedDto"
                }
              }
            }
          }
        }
      },
      "put": {
        "tags": [
          "Led"
        ],
        "parameters": [
          {
            "name": "id",
            "in": "path",
            "required": true,
            "schema": {
              "type": "integer",
              "format": "int32"
            }
          }
        ],
        "requestBody": {
          "content": {
            "application/json": {
              "schema": {
                "$ref": "#/components/schemas/UpdateLedDto"
              }
            },
            "text/json": {
              "schema": {
                "$ref": "#/components/schemas/UpdateLedDto"
              }
            },
            "application/*+json": {
              "schema": {
                "$ref": "#/components/schemas/UpdateLedDto"
              }
            }
          }
        },
        "responses": {
          "200": {
            "description": "OK",
            "content": {
              "text/plain": {
                "schema": {
                  "$ref": "#/components/schemas/LedDto"
                }
              },
              "application/json": {
                "schema": {
                  "$ref": "#/components/schemas/LedDto"
                }
              },
              "text/json": {
                "schema": {
                  "$ref": "#/components/schemas/LedDto"
                }
              }
            }
          }
        }
      },
      "delete": {
        "tags": [
          "Led"
        ],
        "parameters": [
          {
            "name": "id",
            "in": "path",
            "required": true,
            "schema": {
              "type": "integer",
              "format": "int32"
            }
          }
        ],
        "responses": {
          "200": {
            "description": "OK"
          }
        }
      }
    }
  },
  "components": {
    "schemas": {
      "CameraDto": {
        "type": "object",
        "properties": {
          "id": {
            "type": "integer",
            "format": "int32"
          },
          "name": {
            "type": "string",
            "nullable": true
          },
          "code": {
            "type": "string",
            "nullable": true
          },
          "ipAddress": {
            "type": "string",
            "nullable": true
          },
          "resolution": {
            "type": "string",
            "nullable": true
          },
          "type": {
            "$ref": "#/components/schemas/CameraType"
          },
          "username": {
            "type": "string",
            "nullable": true
          },
          "password": {
            "type": "string",
            "nullable": true
          },
          "computerId": {
            "type": "integer",
            "format": "int32"
          },
          "status": {
            "type": "boolean"
          },
          "createdAt": {
            "type": "string",
            "format": "date-time"
          },
          "updatedAt": {
            "type": "string",
            "format": "date-time"
          }
        },
        "additionalProperties": false
      },
      "CameraType": {
        "enum": [
          "Secus",
          "Shany",
          "Bosch",
          "Vantech",
          "CNB",
          "HIK",
          "Enster",
          "Dahua",
          "Hanse",
          "Tiandy",
          "DMAX",
          "Vivantek"
        ],
        "type": "string"
      },
      "ComputerDto": {
        "type": "object",
        "properties": {
          "id": {
            "type": "integer",
            "format": "int32"
          },
          "name": {
            "type": "string",
            "nullable": true
          },
          "ipAddress": {
            "type": "string",
            "nullable": true
          },
          "gateId": {
            "type": "integer",
            "format": "int32",
            "nullable": true
          },
          "status": {
            "type": "boolean"
          },
          "createdAt": {
            "type": "string",
            "format": "date-time"
          },
          "updatedAt": {
            "type": "string",
            "format": "date-time"
          }
        },
        "additionalProperties": false
      },
      "ControlUnitConnectionProtocolType": {
        "enum": [
          "TCP_IP",
          "RS232_485_422"
        ],
        "type": "string"
      },
      "ControlUnitDto": {
        "type": "object",
        "properties": {
          "id": {
            "type": "integer",
            "format": "int32"
          },
          "name": {
            "type": "string",
            "nullable": true
          },
          "code": {
            "type": "string",
            "nullable": true
          },
          "username": {
            "type": "string",
            "nullable": true
          },
          "password": {
            "type": "string",
            "nullable": true
          },
          "comport": {
            "type": "string",
            "nullable": true
          },
          "baudrate": {
            "type": "integer",
            "format": "int32",
            "nullable": true
          },
          "type": {
            "$ref": "#/components/schemas/ControlUnitType"
          },
          "connectionProtocol": {
            "$ref": "#/components/schemas/ControlUnitConnectionProtocolType"
          },
          "computerId": {
            "type": "integer",
            "format": "int32"
          },
          "status": {
            "type": "boolean"
          },
          "createdAt": {
            "type": "string",
            "format": "date-time"
          },
          "updatedAt": {
            "type": "string",
            "format": "date-time"
          }
        },
        "additionalProperties": false
      },
      "ControlUnitType": {
        "enum": [
          "IDTECK",
          "KZE02DOTNET",
          "KZE16DOTNET",
          "MT166",
          "INGRESSUS",
          "E02DOTNET",
          "SC200",
          "Dahua"
        ],
        "type": "string"
      },
      "CreateCameraDto": {
        "type": "object",
        "properties": {
          "name": {
            "type": "string",
            "nullable": true
          },
          "code": {
            "type": "string",
            "nullable": true
          },
          "ipAddress": {
            "type": "string",
            "nullable": true
          },
          "resolution": {
            "type": "string",
            "nullable": true
          },
          "type": {
            "$ref": "#/components/schemas/CameraType"
          },
          "username": {
            "type": "string",
            "nullable": true
          },
          "password": {
            "type": "string",
            "nullable": true
          },
          "computerId": {
            "type": "integer",
            "format": "int32"
          },
          "status": {
            "type": "boolean"
          }
        },
        "additionalProperties": false
      },
      "CreateComputerDto": {
        "type": "object",
        "properties": {
          "name": {
            "type": "string",
            "nullable": true
          },
          "ipAddress": {
            "type": "string",
            "nullable": true
          },
          "gateId": {
            "type": "integer",
            "format": "int32"
          },
          "status": {
            "type": "boolean"
          }
        },
        "additionalProperties": false
      },
      "CreateControlUnitDto": {
        "type": "object",
        "properties": {
          "name": {
            "type": "string",
            "nullable": true
          },
          "code": {
            "type": "string",
            "nullable": true
          },
          "username": {
            "type": "string",
            "nullable": true
          },
          "password": {
            "type": "string",
            "nullable": true
          },
          "comport": {
            "type": "string",
            "nullable": true
          },
          "baudrate": {
            "type": "integer",
            "format": "int32",
            "nullable": true
          },
          "type": {
            "$ref": "#/components/schemas/ControlUnitType"
          },
          "connectionProtocol": {
            "$ref": "#/components/schemas/ControlUnitConnectionProtocolType"
          },
          "computerId": {
            "type": "integer",
            "format": "int32"
          },
          "status": {
            "type": "boolean"
          }
        },
        "additionalProperties": false
      },
      "CreateCustomerDto": {
        "type": "object",
        "properties": {
          "code": {
            "type": "string",
            "nullable": true
          },
          "name": {
            "type": "string",
            "nullable": true
          },
          "phone": {
            "type": "string",
            "nullable": true
          },
          "address": {
            "type": "string",
            "nullable": true
          },
          "customerGroupId": {
            "type": "integer",
            "format": "int32",
            "nullable": true
          }
        },
        "additionalProperties": false
      },
      "CreateCustomerGroupDto": {
        "type": "object",
        "properties": {
          "code": {
            "type": "string",
            "nullable": true
          },
          "name": {
            "type": "string",
            "nullable": true
          }
        },
        "additionalProperties": false
      },
      "CreateGateDto": {
        "type": "object",
        "properties": {
          "name": {
            "type": "string",
            "nullable": true
          },
          "code": {
            "type": "string",
            "nullable": true
          },
          "status": {
            "type": "boolean"
          }
        },
        "additionalProperties": false
      },
      "CreateLaneCameraDto": {
        "type": "object",
        "properties": {
          "cameraId": {
            "type": "integer",
            "format": "int32"
          },
          "purpose": {
            "$ref": "#/components/schemas/LaneCameraPurpose"
          },
          "displayPosition": {
            "type": "integer",
            "format": "int32"
          }
        },
        "additionalProperties": false
      },
      "CreateLaneControlUnitDto": {
        "type": "object",
        "properties": {
          "controlUnitId": {
            "type": "integer",
            "format": "int32"
          },
          "reader": {
            "type": "string",
            "nullable": true
          },
          "input": {
            "type": "string",
            "nullable": true
          },
          "barrier": {
            "type": "string",
            "nullable": true
          },
          "alarm": {
            "type": "string",
            "nullable": true
          }
        },
        "additionalProperties": false
      },
      "CreateLaneDto": {
        "type": "object",
        "properties": {
          "name": {
            "type": "string",
            "nullable": true
          },
          "code": {
            "type": "string",
            "nullable": true
          },
          "type": {
            "$ref": "#/components/schemas/LaneType"
          },
          "reverseLane": {
            "type": "integer",
            "format": "int32",
            "nullable": true
          },
          "computerId": {
            "type": "integer",
            "format": "int32"
          },
          "autoOpenBarrier": {
            "$ref": "#/components/schemas/LaneAutoOpenBarrier"
          },
          "loop": {
            "type": "boolean"
          },
          "displayLed": {
            "type": "boolean"
          },
          "status": {
            "type": "boolean"
          },
          "laneCameras": {
            "type": "array",
            "items": {
              "$ref": "#/components/schemas/CreateLaneCameraDto"
            },
            "nullable": true
          },
          "laneControlUnits": {
            "type": "array",
            "items": {
              "$ref": "#/components/schemas/CreateLaneControlUnitDto"
            },
            "nullable": true
          }
        },
        "additionalProperties": false
      },
      "CreateLedDto": {
        "type": "object",
        "properties": {
          "name": {
            "type": "string",
            "nullable": true
          },
          "code": {
            "type": "string",
            "nullable": true
          },
          "computerId": {
            "type": "integer",
            "format": "int32"
          },
          "comport": {
            "type": "string",
            "nullable": true
          },
          "baudrate": {
            "type": "integer",
            "format": "int32"
          },
          "type": {
            "$ref": "#/components/schemas/LedType"
          },
          "status": {
            "type": "boolean"
          }
        },
        "additionalProperties": false
      },
      "CustomerDto": {
        "type": "object",
        "properties": {
          "id": {
            "type": "integer",
            "format": "int32"
          },
          "code": {
            "type": "string",
            "nullable": true
          },
          "name": {
            "type": "string",
            "nullable": true
          },
          "phone": {
            "type": "string",
            "nullable": true
          },
          "address": {
            "type": "string",
            "nullable": true
          },
          "customerGroupId": {
            "type": "integer",
            "format": "int32",
            "nullable": true
          },
          "createdAt": {
            "type": "string",
            "format": "date-time"
          },
          "updatedAt": {
            "type": "string",
            "format": "date-time"
          }
        },
        "additionalProperties": false
      },
      "CustomerGroupDto": {
        "type": "object",
        "properties": {
          "id": {
            "type": "integer",
            "format": "int32"
          },
          "code": {
            "type": "string",
            "nullable": true
          },
          "name": {
            "type": "string",
            "nullable": true
          },
          "createdAt": {
            "type": "string",
            "format": "date-time"
          },
          "updatedAt": {
            "type": "string",
            "format": "date-time"
          }
        },
        "additionalProperties": false
      },
      "GateDto": {
        "type": "object",
        "properties": {
          "id": {
            "type": "integer",
            "format": "int32"
          },
          "name": {
            "type": "string",
            "nullable": true
          },
          "code": {
            "type": "string",
            "nullable": true
          },
          "status": {
            "type": "boolean"
          },
          "createdAt": {
            "type": "string",
            "format": "date-time"
          },
          "updatedAt": {
            "type": "string",
            "format": "date-time"
          }
        },
        "additionalProperties": false
      },
      "LaneAutoOpenBarrier": {
        "enum": [
          "WhenValid",
          "Never",
          "Always",
          "WhenValidVehicle"
        ],
        "type": "string"
      },
      "LaneCameraDto": {
        "type": "object",
        "properties": {
          "id": {
            "type": "integer",
            "format": "int32"
          },
          "laneId": {
            "type": "integer",
            "format": "int32"
          },
          "cameraId": {
            "type": "integer",
            "format": "int32"
          },
          "purpose": {
            "$ref": "#/components/schemas/LaneCameraPurpose"
          },
          "displayPosition": {
            "type": "integer",
            "format": "int32"
          },
          "createdAt": {
            "type": "string",
            "format": "date-time"
          },
          "updatedAt": {
            "type": "string",
            "format": "date-time"
          }
        },
        "additionalProperties": false
      },
      "LaneCameraPurpose": {
        "enum": [
          "MotorbikePlateNumber",
          "CarPlateNumber",
          "Panorama",
          "Other"
        ],
        "type": "string"
      },
      "LaneControlUnitDto": {
        "type": "object",
        "properties": {
          "id": {
            "type": "integer",
            "format": "int32"
          },
          "laneId": {
            "type": "integer",
            "format": "int32"
          },
          "controlUnitId": {
            "type": "integer",
            "format": "int32"
          },
          "reader": {
            "type": "string",
            "nullable": true
          },
          "input": {
            "type": "string",
            "nullable": true
          },
          "barrier": {
            "type": "string",
            "nullable": true
          },
          "alarm": {
            "type": "string",
            "nullable": true
          },
          "createdAt": {
            "type": "string",
            "format": "date-time"
          },
          "updatedAt": {
            "type": "string",
            "format": "date-time"
          }
        },
        "additionalProperties": false
      },
      "LaneDto": {
        "type": "object",
        "properties": {
          "id": {
            "type": "integer",
            "format": "int32"
          },
          "name": {
            "type": "string",
            "nullable": true
          },
          "code": {
            "type": "string",
            "nullable": true
          },
          "type": {
            "$ref": "#/components/schemas/LaneType"
          },
          "reverseLane": {
            "type": "integer",
            "format": "int32",
            "nullable": true
          },
          "computerId": {
            "type": "integer",
            "format": "int32"
          },
          "autoOpenBarrier": {
            "$ref": "#/components/schemas/LaneAutoOpenBarrier"
          },
          "loop": {
            "type": "boolean"
          },
          "displayLed": {
            "type": "boolean"
          },
          "status": {
            "type": "boolean"
          },
          "createdAt": {
            "type": "string",
            "format": "date-time"
          },
          "updatedAt": {
            "type": "string",
            "format": "date-time"
          },
          "laneCameras": {
            "type": "array",
            "items": {
              "$ref": "#/components/schemas/LaneCameraDto"
            },
            "nullable": true
          },
          "laneControlUnits": {
            "type": "array",
            "items": {
              "$ref": "#/components/schemas/LaneControlUnitDto"
            },
            "nullable": true
          }
        },
        "additionalProperties": false
      },
      "LaneType": {
        "enum": [
          "In",
          "Out",
          "KioskIn",
          "Dynamic"
        ],
        "type": "string"
      },
      "LedDto": {
        "type": "object",
        "properties": {
          "id": {
            "type": "integer",
            "format": "int32"
          },
          "name": {
            "type": "string",
            "nullable": true
          },
          "code": {
            "type": "string",
            "nullable": true
          },
          "computerId": {
            "type": "integer",
            "format": "int32"
          },
          "comport": {
            "type": "string",
            "nullable": true
          },
          "baudrate": {
            "type": "integer",
            "format": "int32"
          },
          "type": {
            "$ref": "#/components/schemas/LedType"
          },
          "status": {
            "type": "boolean"
          },
          "createdAt": {
            "type": "string",
            "format": "date-time"
          },
          "updatedAt": {
            "type": "string",
            "format": "date-time",
            "nullable": true
          }
        },
        "additionalProperties": false
      },
      "LedType": {
        "enum": [
          "P10Red",
          "P10FullColor",
          "P762Rgy",
          "DirectionLed",
          "Huidu"
        ],
        "type": "string"
      },
      "UpdateCameraDto": {
        "type": "object",
        "properties": {
          "name": {
            "type": "string",
            "nullable": true
          },
          "code": {
            "type": "string",
            "nullable": true
          },
          "ipAddress": {
            "type": "string",
            "nullable": true
          },
          "resolution": {
            "type": "string",
            "nullable": true
          },
          "type": {
            "$ref": "#/components/schemas/CameraType"
          },
          "username": {
            "type": "string",
            "nullable": true
          },
          "password": {
            "type": "string",
            "nullable": true
          },
          "computerId": {
            "type": "integer",
            "format": "int32"
          },
          "status": {
            "type": "boolean"
          }
        },
        "additionalProperties": false
      },
      "UpdateComputerDto": {
        "type": "object",
        "properties": {
          "name": {
            "type": "string",
            "nullable": true
          },
          "ipAddress": {
            "type": "string",
            "nullable": true
          },
          "gateId": {
            "type": "integer",
            "format": "int32"
          },
          "status": {
            "type": "boolean"
          }
        },
        "additionalProperties": false
      },
      "UpdateControlUnitDto": {
        "type": "object",
        "properties": {
          "name": {
            "type": "string",
            "nullable": true
          },
          "code": {
            "type": "string",
            "nullable": true
          },
          "username": {
            "type": "string",
            "nullable": true
          },
          "password": {
            "type": "string",
            "nullable": true
          },
          "comport": {
            "type": "string",
            "nullable": true
          },
          "baudrate": {
            "type": "integer",
            "format": "int32",
            "nullable": true
          },
          "type": {
            "$ref": "#/components/schemas/ControlUnitType"
          },
          "connectionProtocol": {
            "$ref": "#/components/schemas/ControlUnitConnectionProtocolType"
          },
          "computerId": {
            "type": "integer",
            "format": "int32"
          },
          "status": {
            "type": "boolean"
          }
        },
        "additionalProperties": false
      },
      "UpdateCustomerDto": {
        "type": "object",
        "properties": {
          "code": {
            "type": "string",
            "nullable": true
          },
          "name": {
            "type": "string",
            "nullable": true
          },
          "phone": {
            "type": "string",
            "nullable": true
          },
          "address": {
            "type": "string",
            "nullable": true
          },
          "customerGroupId": {
            "type": "integer",
            "format": "int32",
            "nullable": true
          }
        },
        "additionalProperties": false
      },
      "UpdateCustomerGroupDto": {
        "type": "object",
        "properties": {
          "code": {
            "type": "string",
            "nullable": true
          },
          "name": {
            "type": "string",
            "nullable": true
          }
        },
        "additionalProperties": false
      },
      "UpdateGateDto": {
        "type": "object",
        "properties": {
          "name": {
            "type": "string",
            "nullable": true
          },
          "code": {
            "type": "string",
            "nullable": true
          },
          "status": {
            "type": "boolean"
          }
        },
        "additionalProperties": false
      },
      "UpdateLaneCameraDto": {
        "type": "object",
        "properties": {
          "cameraId": {
            "type": "integer",
            "format": "int32"
          },
          "purpose": {
            "$ref": "#/components/schemas/LaneCameraPurpose"
          },
          "displayPosition": {
            "type": "integer",
            "format": "int32"
          }
        },
        "additionalProperties": false
      },
      "UpdateLaneControlUnitDto": {
        "type": "object",
        "properties": {
          "controlUnitId": {
            "type": "integer",
            "format": "int32"
          },
          "reader": {
            "type": "string",
            "nullable": true
          },
          "input": {
            "type": "string",
            "nullable": true
          },
          "barrier": {
            "type": "string",
            "nullable": true
          },
          "alarm": {
            "type": "string",
            "nullable": true
          }
        },
        "additionalProperties": false
      },
      "UpdateLaneDto": {
        "type": "object",
        "properties": {
          "name": {
            "type": "string",
            "nullable": true
          },
          "code": {
            "type": "string",
            "nullable": true
          },
          "type": {
            "$ref": "#/components/schemas/LaneType"
          },
          "reverseLane": {
            "type": "integer",
            "format": "int32",
            "nullable": true
          },
          "computerId": {
            "type": "integer",
            "format": "int32"
          },
          "autoOpenBarrier": {
            "$ref": "#/components/schemas/LaneAutoOpenBarrier"
          },
          "loop": {
            "type": "boolean"
          },
          "displayLed": {
            "type": "boolean"
          },
          "status": {
            "type": "boolean"
          },
          "laneCameras": {
            "type": "array",
            "items": {
              "$ref": "#/components/schemas/UpdateLaneCameraDto"
            },
            "nullable": true
          },
          "laneControlUnits": {
            "type": "array",
            "items": {
              "$ref": "#/components/schemas/UpdateLaneControlUnitDto"
            },
            "nullable": true
          }
        },
        "additionalProperties": false
      },
      "UpdateLedDto": {
        "type": "object",
        "properties": {
          "name": {
            "type": "string",
            "nullable": true
          },
          "code": {
            "type": "string",
            "nullable": true
          },
          "computerId": {
            "type": "integer",
            "format": "int32"
          },
          "comport": {
            "type": "string",
            "nullable": true
          },
          "baudrate": {
            "type": "integer",
            "format": "int32"
          },
          "type": {
            "$ref": "#/components/schemas/LedType"
          },
          "status": {
            "type": "boolean"
          }
        },
        "additionalProperties": false
      }
    }
  }
}